amshorelineone/__init__.py
amshorelineone/sleep.py
amshorelineone-1.2.dist-info/METADATA
amshorelineone-1.2.dist-info/RECORD
amshorelineone-1.2.dist-info/WHEEL
amshorelineone-1.2.dist-info/top_level.txt
src/__init__.py
src/running.py
