Metadata-Version: 2.1
Name: amshorelineone
Version: 1.2
Summary: hiahia
Home-page: https://github//
Author: amshoreline
Author-email: 371350508@qq.com
License: UNKNOWN
Platform: UNKNOWN
